tarjinja/__init__.py
tarjinja/_cli.py
tarjinja/_debug.py
tarjinja/choice.py
tarjinja/dictio.py
tarjinja/dirtree.py
tarjinja/expand.py
tarjinja/git.py
tarjinja/iface.py
tarjinja/jinjafilter.py
tarjinja/makofilter.py
tarjinja/multifilter.py
tarjinja/nullfilter.py
tarjinja/reversefilter.py
tarjinja/strfilter.py
tarjinja/tar.py
tarjinja/version.py
tarjinja/zip.py
tarjinja-0.0.6.dist-info/LICENSE
tarjinja-0.0.6.dist-info/METADATA
tarjinja-0.0.6.dist-info/WHEEL
tarjinja-0.0.6.dist-info/entry_points.txt
tarjinja-0.0.6.dist-info/top_level.txt
tarjinja-0.0.6.dist-info/RECORD
