Metadata-Version: 2.1
Name: tarjinja
Version: 0.0.6
Summary: archive/recursive copy with template
Home-page: https://github.com/wtnb75/tarjinja
Author: Takashi WATANABE
Author-email: wtnb75@gmail.com
License: MIT
Platform: UNKNOWN
Classifier: Development Status :: 3 - Alpha
Classifier: Intended Audience :: Developers
Classifier: License :: OSI Approved :: MIT License
Classifier: Topic :: Software Development :: Libraries :: Python Modules
Classifier: Programming Language :: Python :: 3
Requires-Dist: Jinja2
Requires-Dist: Click
Requires-Dist: braceexpand
Requires-Dist: PyYAML
Requires-Dist: mako
Requires-Dist: requests
Requires-Dist: GitPython
